{
  "id": 16650,
  "cuisine": "NorthAmerican",
  "ingredients": [
    "beer",
    "garlic",
    "cream_cheese",
    "mozzarella_cheese",
    "cheddar_cheese",
    "rye_bread"
  ],
  "score_avg": 59.13333333333333,
  "pair_coverage": 1.0,
  "heatmap": [
    {
      "x": "beer",
      "y": "beer",
      "value": 0
    },
    {
      "x": "beer",
      "y": "garlic",
      "value": 7
    },
    {
      "x": "beer",
      "y": "cream_cheese",
      "value": 87
    },
    {
      "x": "beer",
      "y": "mozzarella_cheese",
      "value": 90
    },
    {
      "x": "beer",
      "y": "cheddar_cheese",
      "value": 97
    },
    {
      "x": "beer",
      "y": "rye_bread",
      "value": 60
    },
    {
      "x": "garlic",
      "y": "beer",
      "value": 7
    },
    {
      "x": "garlic",
      "y": "garlic",
      "value": 0
    },
    {
      "x": "garlic",
      "y": "cream_cheese",
      "value": 5
    },
    {
      "x": "garlic",
      "y": "mozzarella_cheese",
      "value": 5
    },
    {
      "x": "garlic",
      "y": "cheddar_cheese",
      "value": 6
    },
    {
      "x": "garlic",
      "y": "rye_bread",
      "value": 3
    },
    {
      "x": "cream_cheese",
      "y": "beer",
      "value": 87
    },
    {
      "x": "cream_cheese",
      "y": "garlic",
      "value": 5
    },
    {
      "x": "cream_cheese",
      "y": "cream_cheese",
      "value": 0
    },
    {
      "x": "cream_cheese",
      "y": "mozzarella_cheese",
      "value": 127
    },
    {
      "x": "cream_cheese",
      "y": "cheddar_cheese",
      "value": 130
    },
    {
      "x": "cream_cheese",
      "y": "rye_bread",
      "value": 47
    },
    {
      "x": "mozzarella_cheese",
      "y": "beer",
      "value": 90
    },
    {
      "x": "mozzarella_cheese",
      "y": "garlic",
      "value": 5
    },
    {
      "x": "mozzarella_cheese",
      "y": "cream_cheese",
      "value": 127
    },
    {
      "x": "mozzarella_cheese",
      "y": "mozzarella_cheese",
      "value": 0
    },
    {
      "x": "mozzarella_cheese",
      "y": "cheddar_cheese",
      "value": 127
    },
    {
      "x": "mozzarella_cheese",
      "y": "rye_bread",
      "value": 46
    },
    {
      "x": "cheddar_cheese",
      "y": "beer",
      "value": 97
    },
    {
      "x": "cheddar_cheese",
      "y": "garlic",
      "value": 6
    },
    {
      "x": "cheddar_cheese",
      "y": "cream_cheese",
      "value": 130
    },
    {
      "x": "cheddar_cheese",
      "y": "mozzarella_cheese",
      "value": 127
    },
    {
      "x": "cheddar_cheese",
      "y": "cheddar_cheese",
      "value": 0
    },
    {
      "x": "cheddar_cheese",
      "y": "rye_bread",
      "value": 50
    },
    {
      "x": "rye_bread",
      "y": "beer",
      "value": 60
    },
    {
      "x": "rye_bread",
      "y": "garlic",
      "value": 3
    },
    {
      "x": "rye_bread",
      "y": "cream_cheese",
      "value": 47
    },
    {
      "x": "rye_bread",
      "y": "mozzarella_cheese",
      "value": 46
    },
    {
      "x": "rye_bread",
      "y": "cheddar_cheese",
      "value": 50
    },
    {
      "x": "rye_bread",
      "y": "rye_bread",
      "value": 0
    }
  ],
  "contributions": [
    {
      "ingredient": "cheddar_cheese",
      "mean": 82.0
    },
    {
      "ingredient": "cream_cheese",
      "mean": 79.2
    },
    {
      "ingredient": "mozzarella_cheese",
      "mean": 79.0
    },
    {
      "ingredient": "beer",
      "mean": 68.2
    },
    {
      "ingredient": "rye_bread",
      "mean": 41.2
    },
    {
      "ingredient": "garlic",
      "mean": 5.2
    }
  ]
}