{
  "id": 29825,
  "cuisine": "NorthAmerican",
  "ingredients": [
    "dill",
    "wheat",
    "yeast",
    "chive",
    "cucumber",
    "cream"
  ],
  "score_avg": 1.0,
  "pair_coverage": 0.4,
  "heatmap": [
    {
      "x": "dill",
      "y": "dill",
      "value": 0
    },
    {
      "x": "dill",
      "y": "wheat",
      "value": 0
    },
    {
      "x": "dill",
      "y": "yeast",
      "value": 0
    },
    {
      "x": "dill",
      "y": "chive",
      "value": 4
    },
    {
      "x": "dill",
      "y": "cucumber",
      "value": 3
    },
    {
      "x": "dill",
      "y": "cream",
      "value": 3
    },
    {
      "x": "wheat",
      "y": "dill",
      "value": 0
    },
    {
      "x": "wheat",
      "y": "wheat",
      "value": 0
    },
    {
      "x": "wheat",
      "y": "yeast",
      "value": 0
    },
    {
      "x": "wheat",
      "y": "chive",
      "value": 0
    },
    {
      "x": "wheat",
      "y": "cucumber",
      "value": 0
    },
    {
      "x": "wheat",
      "y": "cream",
      "value": 1
    },
    {
      "x": "yeast",
      "y": "dill",
      "value": 0
    },
    {
      "x": "yeast",
      "y": "wheat",
      "value": 0
    },
    {
      "x": "yeast",
      "y": "yeast",
      "value": 0
    },
    {
      "x": "yeast",
      "y": "chive",
      "value": 0
    },
    {
      "x": "yeast",
      "y": "cucumber",
      "value": 0
    },
    {
      "x": "yeast",
      "y": "cream",
      "value": 0
    },
    {
      "x": "chive",
      "y": "dill",
      "value": 4
    },
    {
      "x": "chive",
      "y": "wheat",
      "value": 0
    },
    {
      "x": "chive",
      "y": "yeast",
      "value": 0
    },
    {
      "x": "chive",
      "y": "chive",
      "value": 0
    },
    {
      "x": "chive",
      "y": "cucumber",
      "value": 0
    },
    {
      "x": "chive",
      "y": "cream",
      "value": 1
    },
    {
      "x": "cucumber",
      "y": "dill",
      "value": 3
    },
    {
      "x": "cucumber",
      "y": "wheat",
      "value": 0
    },
    {
      "x": "cucumber",
      "y": "yeast",
      "value": 0
    },
    {
      "x": "cucumber",
      "y": "chive",
      "value": 0
    },
    {
      "x": "cucumber",
      "y": "cucumber",
      "value": 0
    },
    {
      "x": "cucumber",
      "y": "cream",
      "value": 3
    },
    {
      "x": "cream",
      "y": "dill",
      "value": 3
    },
    {
      "x": "cream",
      "y": "wheat",
      "value": 1
    },
    {
      "x": "cream",
      "y": "yeast",
      "value": 0
    },
    {
      "x": "cream",
      "y": "chive",
      "value": 1
    },
    {
      "x": "cream",
      "y": "cucumber",
      "value": 3
    },
    {
      "x": "cream",
      "y": "cream",
      "value": 0
    }
  ],
  "contributions": [
    {
      "ingredient": "dill",
      "mean": 2.0
    },
    {
      "ingredient": "cream",
      "mean": 1.6
    },
    {
      "ingredient": "cucumber",
      "mean": 1.2
    },
    {
      "ingredient": "chive",
      "mean": 1.0
    },
    {
      "ingredient": "wheat",
      "mean": 0.2
    },
    {
      "ingredient": "yeast",
      "mean": 0.0
    }
  ]
}