{
  "id": 5427,
  "cuisine": "LatinAmerican",
  "ingredients": [
    "coriander",
    "lemon_juice",
    "bell_pepper",
    "corn",
    "avocado",
    "scallion"
  ],
  "score_avg": 4.733333333333333,
  "pair_coverage": 0.4666666666666667,
  "heatmap": [
    {
      "x": "coriander",
      "y": "coriander",
      "value": 0
    },
    {
      "x": "coriander",
      "y": "lemon_juice",
      "value": 0
    },
    {
      "x": "coriander",
      "y": "bell_pepper",
      "value": 19
    },
    {
      "x": "coriander",
      "y": "corn",
      "value": 10
    },
    {
      "x": "coriander",
      "y": "avocado",
      "value": 9
    },
    {
      "x": "coriander",
      "y": "scallion",
      "value": 0
    },
    {
      "x": "lemon_juice",
      "y": "coriander",
      "value": 0
    },
    {
      "x": "lemon_juice",
      "y": "lemon_juice",
      "value": 0
    },
    {
      "x": "lemon_juice",
      "y": "bell_pepper",
      "value": 1
    },
    {
      "x": "lemon_juice",
      "y": "corn",
      "value": 0
    },
    {
      "x": "lemon_juice",
      "y": "avocado",
      "value": 0
    },
    {
      "x": "lemon_juice",
      "y": "scallion",
      "value": 0
    },
    {
      "x": "bell_pepper",
      "y": "coriander",
      "value": 19
    },
    {
      "x": "bell_pepper",
      "y": "lemon_juice",
      "value": 1
    },
    {
      "x": "bell_pepper",
      "y": "bell_pepper",
      "value": 0
    },
    {
      "x": "bell_pepper",
      "y": "corn",
      "value": 13
    },
    {
      "x": "bell_pepper",
      "y": "avocado",
      "value": 6
    },
    {
      "x": "bell_pepper",
      "y": "scallion",
      "value": 0
    },
    {
      "x": "corn",
      "y": "coriander",
      "value": 10
    },
    {
      "x": "corn",
      "y": "lemon_juice",
      "value": 0
    },
    {
      "x": "corn",
      "y": "bell_pepper",
      "value": 13
    },
    {
      "x": "corn",
      "y": "corn",
      "value": 0
    },
    {
      "x": "corn",
      "y": "avocado",
      "value": 13
    },
    {
      "x": "corn",
      "y": "scallion",
      "value": 0
    },
    {
      "x": "avocado",
      "y": "coriander",
      "value": 9
    },
    {
      "x": "avocado",
      "y": "lemon_juice",
      "value": 0
    },
    {
      "x": "avocado",
      "y": "bell_pepper",
      "value": 6
    },
    {
      "x": "avocado",
      "y": "corn",
      "value": 13
    },
    {
      "x": "avocado",
      "y": "avocado",
      "value": 0
    },
    {
      "x": "avocado",
      "y": "scallion",
      "value": 0
    },
    {
      "x": "scallion",
      "y": "coriander",
      "value": 0
    },
    {
      "x": "scallion",
      "y": "lemon_juice",
      "value": 0
    },
    {
      "x": "scallion",
      "y": "bell_pepper",
      "value": 0
    },
    {
      "x": "scallion",
      "y": "corn",
      "value": 0
    },
    {
      "x": "scallion",
      "y": "avocado",
      "value": 0
    },
    {
      "x": "scallion",
      "y": "scallion",
      "value": 0
    }
  ],
  "contributions": [
    {
      "ingredient": "bell_pepper",
      "mean": 7.8
    },
    {
      "ingredient": "coriander",
      "mean": 7.6
    },
    {
      "ingredient": "corn",
      "mean": 7.2
    },
    {
      "ingredient": "avocado",
      "mean": 5.6
    },
    {
      "ingredient": "lemon_juice",
      "mean": 0.2
    },
    {
      "ingredient": "scallion",
      "mean": 0.0
    }
  ]
}