{
  "id": 29003,
  "cuisine": "NorthAmerican",
  "ingredients": [
    "butter",
    "cheddar_cheese",
    "wheat",
    "milk",
    "onion"
  ],
  "score_avg": 28.3,
  "pair_coverage": 0.8,
  "heatmap": [
    {
      "x": "butter",
      "y": "butter",
      "value": 0
    },
    {
      "x": "butter",
      "y": "cheddar_cheese",
      "value": 71
    },
    {
      "x": "butter",
      "y": "wheat",
      "value": 1
    },
    {
      "x": "butter",
      "y": "milk",
      "value": 74
    },
    {
      "x": "butter",
      "y": "onion",
      "value": 15
    },
    {
      "x": "cheddar_cheese",
      "y": "butter",
      "value": 71
    },
    {
      "x": "cheddar_cheese",
      "y": "cheddar_cheese",
      "value": 0
    },
    {
      "x": "cheddar_cheese",
      "y": "wheat",
      "value": 4
    },
    {
      "x": "cheddar_cheese",
      "y": "milk",
      "value": 76
    },
    {
      "x": "cheddar_cheese",
      "y": "onion",
      "value": 20
    },
    {
      "x": "wheat",
      "y": "butter",
      "value": 1
    },
    {
      "x": "wheat",
      "y": "cheddar_cheese",
      "value": 4
    },
    {
      "x": "wheat",
      "y": "wheat",
      "value": 0
    },
    {
      "x": "wheat",
      "y": "milk",
      "value": 0
    },
    {
      "x": "wheat",
      "y": "onion",
      "value": 0
    },
    {
      "x": "milk",
      "y": "butter",
      "value": 74
    },
    {
      "x": "milk",
      "y": "cheddar_cheese",
      "value": 76
    },
    {
      "x": "milk",
      "y": "wheat",
      "value": 0
    },
    {
      "x": "milk",
      "y": "milk",
      "value": 0
    },
    {
      "x": "milk",
      "y": "onion",
      "value": 22
    },
    {
      "x": "onion",
      "y": "butter",
      "value": 15
    },
    {
      "x": "onion",
      "y": "cheddar_cheese",
      "value": 20
    },
    {
      "x": "onion",
      "y": "wheat",
      "value": 0
    },
    {
      "x": "onion",
      "y": "milk",
      "value": 22
    },
    {
      "x": "onion",
      "y": "onion",
      "value": 0
    }
  ],
  "contributions": [
    {
      "ingredient": "milk",
      "mean": 43.0
    },
    {
      "ingredient": "cheddar_cheese",
      "mean": 42.75
    },
    {
      "ingredient": "butter",
      "mean": 40.25
    },
    {
      "ingredient": "onion",
      "mean": 14.25
    },
    {
      "ingredient": "wheat",
      "mean": 1.25
    }
  ]
}