{
  "id": 8127,
  "cuisine": "NorthAmerican",
  "ingredients": [
    "melon",
    "olive_oil",
    "lime_juice",
    "tarragon",
    "lime"
  ],
  "score_avg": 3.1,
  "pair_coverage": 0.6,
  "heatmap": [
    {
      "x": "melon",
      "y": "melon",
      "value": 0
    },
    {
      "x": "melon",
      "y": "olive_oil",
      "value": 1
    },
    {
      "x": "melon",
      "y": "lime_juice",
      "value": 1
    },
    {
      "x": "melon",
      "y": "tarragon",
      "value": 0
    },
    {
      "x": "melon",
      "y": "lime",
      "value": 22
    },
    {
      "x": "olive_oil",
      "y": "melon",
      "value": 1
    },
    {
      "x": "olive_oil",
      "y": "olive_oil",
      "value": 0
    },
    {
      "x": "olive_oil",
      "y": "lime_juice",
      "value": 0
    },
    {
      "x": "olive_oil",
      "y": "tarragon",
      "value": 0
    },
    {
      "x": "olive_oil",
      "y": "lime",
      "value": 2
    },
    {
      "x": "lime_juice",
      "y": "melon",
      "value": 1
    },
    {
      "x": "lime_juice",
      "y": "olive_oil",
      "value": 0
    },
    {
      "x": "lime_juice",
      "y": "lime_juice",
      "value": 0
    },
    {
      "x": "lime_juice",
      "y": "tarragon",
      "value": 0
    },
    {
      "x": "lime_juice",
      "y": "lime",
      "value": 2
    },
    {
      "x": "tarragon",
      "y": "melon",
      "value": 0
    },
    {
      "x": "tarragon",
      "y": "olive_oil",
      "value": 0
    },
    {
      "x": "tarragon",
      "y": "lime_juice",
      "value": 0
    },
    {
      "x": "tarragon",
      "y": "tarragon",
      "value": 0
    },
    {
      "x": "tarragon",
      "y": "lime",
      "value": 3
    },
    {
      "x": "lime",
      "y": "melon",
      "value": 22
    },
    {
      "x": "lime",
      "y": "olive_oil",
      "value": 2
    },
    {
      "x": "lime",
      "y": "lime_juice",
      "value": 2
    },
    {
      "x": "lime",
      "y": "tarragon",
      "value": 3
    },
    {
      "x": "lime",
      "y": "lime",
      "value": 0
    }
  ],
  "contributions": [
    {
      "ingredient": "lime",
      "mean": 7.25
    },
    {
      "ingredient": "melon",
      "mean": 6.0
    },
    {
      "ingredient": "olive_oil",
      "mean": 0.75
    },
    {
      "ingredient": "lime_juice",
      "mean": 0.75
    },
    {
      "ingredient": "tarragon",
      "mean": 0.75
    }
  ]
}