{
  "id": 1559,
  "cuisine": "EastAsian",
  "ingredients": [
    "sesame_oil",
    "beef",
    "sake",
    "shiitake",
    "cayenne",
    "scallion",
    "honey",
    "roasted_sesame_seed",
    "garlic",
    "soybean",
    "rice"
  ],
  "score_avg": 12.145454545454545,
  "pair_coverage": 0.7090909090909091,
  "heatmap": [
    {
      "x": "sesame_oil",
      "y": "sesame_oil",
      "value": 0
    },
    {
      "x": "sesame_oil",
      "y": "beef",
      "value": 3
    },
    {
      "x": "sesame_oil",
      "y": "sake",
      "value": 0
    },
    {
      "x": "sesame_oil",
      "y": "shiitake",
      "value": 2
    },
    {
      "x": "sesame_oil",
      "y": "cayenne",
      "value": 0
    },
    {
      "x": "sesame_oil",
      "y": "scallion",
      "value": 0
    },
    {
      "x": "sesame_oil",
      "y": "honey",
      "value": 0
    },
    {
      "x": "sesame_oil",
      "y": "roasted_sesame_seed",
      "value": 0
    },
    {
      "x": "sesame_oil",
      "y": "garlic",
      "value": 1
    },
    {
      "x": "sesame_oil",
      "y": "soybean",
      "value": 2
    },
    {
      "x": "sesame_oil",
      "y": "rice",
      "value": 2
    },
    {
      "x": "beef",
      "y": "sesame_oil",
      "value": 3
    },
    {
      "x": "beef",
      "y": "beef",
      "value": 0
    },
    {
      "x": "beef",
      "y": "sake",
      "value": 18
    },
    {
      "x": "beef",
      "y": "shiitake",
      "value": 65
    },
    {
      "x": "beef",
      "y": "cayenne",
      "value": 4
    },
    {
      "x": "beef",
      "y": "scallion",
      "value": 0
    },
    {
      "x": "beef",
      "y": "honey",
      "value": 23
    },
    {
      "x": "beef",
      "y": "roasted_sesame_seed",
      "value": 17
    },
    {
      "x": "beef",
      "y": "garlic",
      "value": 9
    },
    {
      "x": "beef",
      "y": "soybean",
      "value": 96
    },
    {
      "x": "beef",
      "y": "rice",
      "value": 54
    },
    {
      "x": "sake",
      "y": "sesame_oil",
      "value": 0
    },
    {
      "x": "sake",
      "y": "beef",
      "value": 18
    },
    {
      "x": "sake",
      "y": "sake",
      "value": 0
    },
    {
      "x": "sake",
      "y": "shiitake",
      "value": 14
    },
    {
      "x": "sake",
      "y": "cayenne",
      "value": 0
    },
    {
      "x": "sake",
      "y": "scallion",
      "value": 0
    },
    {
      "x": "sake",
      "y": "honey",
      "value": 6
    },
    {
      "x": "sake",
      "y": "roasted_sesame_seed",
      "value": 2
    },
    {
      "x": "sake",
      "y": "garlic",
      "value": 2
    },
    {
      "x": "sake",
      "y": "soybean",
      "value": 15
    },
    {
      "x": "sake",
      "y": "rice",
      "value": 14
    },
    {
      "x": "shiitake",
      "y": "sesame_oil",
      "value": 2
    },
    {
      "x": "shiitake",
      "y": "beef",
      "value": 65
    },
    {
      "x": "shiitake",
      "y": "sake",
      "value": 14
    },
    {
      "x": "shiitake",
      "y": "shiitake",
      "value": 0
    },
    {
      "x": "shiitake",
      "y": "cayenne",
      "value": 9
    },
    {
      "x": "shiitake",
      "y": "scallion",
      "value": 0
    },
    {
      "x": "shiitake",
      "y": "honey",
      "value": 22
    },
    {
      "x": "shiitake",
      "y": "roasted_sesame_seed",
      "value": 12
    },
    {
      "x": "shiitake",
      "y": "garlic",
      "value": 4
    },
    {
      "x": "shiitake",
      "y": "soybean",
      "value": 68
    },
    {
      "x": "shiitake",
      "y": "rice",
      "value": 44
    },
    {
      "x": "cayenne",
      "y": "sesame_oil",
      "value": 0
    },
    {
      "x": "cayenne",
      "y": "beef",
      "value": 4
    },
    {
      "x": "cayenne",
      "y": "sake",
      "value": 0
    },
    {
      "x": "cayenne",
      "y": "shiitake",
      "value": 9
    },
    {
      "x": "cayenne",
      "y": "cayenne",
      "value": 0
    },
    {
      "x": "cayenne",
      "y": "scallion",
      "value": 0
    },
    {
      "x": "cayenne",
      "y": "honey",
      "value": 6
    },
    {
      "x": "cayenne",
      "y": "roasted_sesame_seed",
      "value": 0
    },
    {
      "x": "cayenne",
      "y": "garlic",
      "value": 1
    },
    {
      "x": "cayenne",
      "y": "soybean",
      "value": 8
    },
    {
      "x": "cayenne",
      "y": "rice",
      "value": 5
    },
    {
      "x": "scallion",
      "y": "sesame_oil",
      "value": 0
    },
    {
      "x": "scallion",
      "y": "beef",
      "value": 0
    },
    {
      "x": "scallion",
      "y": "sake",
      "value": 0
    },
    {
      "x": "scallion",
      "y": "shiitake",
      "value": 0
    },
    {
      "x": "scallion",
      "y": "cayenne",
      "value": 0
    },
    {
      "x": "scallion",
      "y": "scallion",
      "value": 0
    },
    {
      "x": "scallion",
      "y": "honey",
      "value": 0
    },
    {
      "x": "scallion",
      "y": "roasted_sesame_seed",
      "value": 0
    },
    {
      "x": "scallion",
      "y": "garlic",
      "value": 1
    },
    {
      "x": "scallion",
      "y": "soybean",
      "value": 0
    },
    {
      "x": "scallion",
      "y": "rice",
      "value": 0
    },
    {
      "x": "honey",
      "y": "sesame_oil",
      "value": 0
    },
    {
      "x": "honey",
      "y": "beef",
      "value": 23
    },
    {
      "x": "honey",
      "y": "sake",
      "value": 6
    },
    {
      "x": "honey",
      "y": "shiitake",
      "value": 22
    },
    {
      "x": "honey",
      "y": "cayenne",
      "value": 6
    },
    {
      "x": "honey",
      "y": "scallion",
      "value": 0
    },
    {
      "x": "honey",
      "y": "honey",
      "value": 0
    },
    {
      "x": "honey",
      "y": "roasted_sesame_seed",
      "value": 4
    },
    {
      "x": "honey",
      "y": "garlic",
      "value": 1
    },
    {
      "x": "honey",
      "y": "soybean",
      "value": 29
    },
    {
      "x": "honey",
      "y": "rice",
      "value": 13
    },
    {
      "x": "roasted_sesame_seed",
      "y": "sesame_oil",
      "value": 0
    },
    {
      "x": "roasted_sesame_seed",
      "y": "beef",
      "value": 17
    },
    {
      "x": "roasted_sesame_seed",
      "y": "sake",
      "value": 2
    },
    {
      "x": "roasted_sesame_seed",
      "y": "shiitake",
      "value": 12
    },
    {
      "x": "roasted_sesame_seed",
      "y": "cayenne",
      "value": 0
    },
    {
      "x": "roasted_sesame_seed",
      "y": "scallion",
      "value": 0
    },
    {
      "x": "roasted_sesame_seed",
      "y": "honey",
      "value": 4
    },
    {
      "x": "roasted_sesame_seed",
      "y": "roasted_sesame_seed",
      "value": 0
    },
    {
      "x": "roasted_sesame_seed",
      "y": "garlic",
      "value": 0
    },
    {
      "x": "roasted_sesame_seed",
      "y": "soybean",
      "value": 16
    },
    {
      "x": "roasted_sesame_seed",
      "y": "rice",
      "value": 11
    },
    {
      "x": "garlic",
      "y": "sesame_oil",
      "value": 1
    },
    {
      "x": "garlic",
      "y": "beef",
      "value": 9
    },
    {
      "x": "garlic",
      "y": "sake",
      "value": 2
    },
    {
      "x": "garlic",
      "y": "shiitake",
      "value": 4
    },
    {
      "x": "garlic",
      "y": "cayenne",
      "value": 1
    },
    {
      "x": "garlic",
      "y": "scallion",
      "value": 1
    },
    {
      "x": "garlic",
      "y": "honey",
      "value": 1
    },
    {
      "x": "garlic",
      "y": "roasted_sesame_seed",
      "value": 0
    },
    {
      "x": "garlic",
      "y": "garlic",
      "value": 0
    },
    {
      "x": "garlic",
      "y": "soybean",
      "value": 5
    },
    {
      "x": "garlic",
      "y": "rice",
      "value": 5
    },
    {
      "x": "soybean",
      "y": "sesame_oil",
      "value": 2
    },
    {
      "x": "soybean",
      "y": "beef",
      "value": 96
    },
    {
      "x": "soybean",
      "y": "sake",
      "value": 15
    },
    {
      "x": "soybean",
      "y": "shiitake",
      "value": 68
    },
    {
      "x": "soybean",
      "y": "cayenne",
      "value": 8
    },
    {
      "x": "soybean",
      "y": "scallion",
      "value": 0
    },
    {
      "x": "soybean",
      "y": "honey",
      "value": 29
    },
    {
      "x": "soybean",
      "y": "roasted_sesame_seed",
      "value": 16
    },
    {
      "x": "soybean",
      "y": "garlic",
      "value": 5
    },
    {
      "x": "soybean",
      "y": "soybean",
      "value": 0
    },
    {
      "x": "soybean",
      "y": "rice",
      "value": 55
    },
    {
      "x": "rice",
      "y": "sesame_oil",
      "value": 2
    },
    {
      "x": "rice",
      "y": "beef",
      "value": 54
    },
    {
      "x": "rice",
      "y": "sake",
      "value": 14
    },
    {
      "x": "rice",
      "y": "shiitake",
      "value": 44
    },
    {
      "x": "rice",
      "y": "cayenne",
      "value": 5
    },
    {
      "x": "rice",
      "y": "scallion",
      "value": 0
    },
    {
      "x": "rice",
      "y": "honey",
      "value": 13
    },
    {
      "x": "rice",
      "y": "roasted_sesame_seed",
      "value": 11
    },
    {
      "x": "rice",
      "y": "garlic",
      "value": 5
    },
    {
      "x": "rice",
      "y": "soybean",
      "value": 55
    },
    {
      "x": "rice",
      "y": "rice",
      "value": 0
    }
  ],
  "contributions": [
    {
      "ingredient": "soybean",
      "mean": 29.4
    },
    {
      "ingredient": "beef",
      "mean": 28.9
    },
    {
      "ingredient": "shiitake",
      "mean": 24.0
    },
    {
      "ingredient": "rice",
      "mean": 20.3
    },
    {
      "ingredient": "honey",
      "mean": 10.4
    },
    {
      "ingredient": "sake",
      "mean": 7.1
    },
    {
      "ingredient": "roasted_sesame_seed",
      "mean": 6.2
    },
    {
      "ingredient": "cayenne",
      "mean": 3.3
    },
    {
      "ingredient": "garlic",
      "mean": 2.9
    },
    {
      "ingredient": "sesame_oil",
      "mean": 1.0
    },
    {
      "ingredient": "scallion",
      "mean": 0.1
    }
  ]
}