{
  "id": 14413,
  "cuisine": "NorthAmerican",
  "ingredients": [
    "butter",
    "cocoa",
    "corn",
    "almond",
    "milk"
  ],
  "score_avg": 31.6,
  "pair_coverage": 1.0,
  "heatmap": [
    {
      "x": "butter",
      "y": "butter",
      "value": 0
    },
    {
      "x": "butter",
      "y": "cocoa",
      "value": 53
    },
    {
      "x": "butter",
      "y": "corn",
      "value": 35
    },
    {
      "x": "butter",
      "y": "almond",
      "value": 3
    },
    {
      "x": "butter",
      "y": "milk",
      "value": 74
    },
    {
      "x": "cocoa",
      "y": "butter",
      "value": 53
    },
    {
      "x": "cocoa",
      "y": "cocoa",
      "value": 0
    },
    {
      "x": "cocoa",
      "y": "corn",
      "value": 43
    },
    {
      "x": "cocoa",
      "y": "almond",
      "value": 6
    },
    {
      "x": "cocoa",
      "y": "milk",
      "value": 52
    },
    {
      "x": "corn",
      "y": "butter",
      "value": 35
    },
    {
      "x": "corn",
      "y": "cocoa",
      "value": 43
    },
    {
      "x": "corn",
      "y": "corn",
      "value": 0
    },
    {
      "x": "corn",
      "y": "almond",
      "value": 5
    },
    {
      "x": "corn",
      "y": "milk",
      "value": 42
    },
    {
      "x": "almond",
      "y": "butter",
      "value": 3
    },
    {
      "x": "almond",
      "y": "cocoa",
      "value": 6
    },
    {
      "x": "almond",
      "y": "corn",
      "value": 5
    },
    {
      "x": "almond",
      "y": "almond",
      "value": 0
    },
    {
      "x": "almond",
      "y": "milk",
      "value": 3
    },
    {
      "x": "milk",
      "y": "butter",
      "value": 74
    },
    {
      "x": "milk",
      "y": "cocoa",
      "value": 52
    },
    {
      "x": "milk",
      "y": "corn",
      "value": 42
    },
    {
      "x": "milk",
      "y": "almond",
      "value": 3
    },
    {
      "x": "milk",
      "y": "milk",
      "value": 0
    }
  ],
  "contributions": [
    {
      "ingredient": "milk",
      "mean": 42.75
    },
    {
      "ingredient": "butter",
      "mean": 41.25
    },
    {
      "ingredient": "cocoa",
      "mean": 38.5
    },
    {
      "ingredient": "corn",
      "mean": 31.25
    },
    {
      "ingredient": "almond",
      "mean": 4.25
    }
  ]
}