{
  "id": 15457,
  "cuisine": "NorthAmerican",
  "ingredients": [
    "wheat",
    "cream_cheese",
    "yeast",
    "rosemary",
    "egg",
    "milk"
  ],
  "score_avg": 9.466666666666667,
  "pair_coverage": 0.5333333333333333,
  "heatmap": [
    {
      "x": "wheat",
      "y": "wheat",
      "value": 0
    },
    {
      "x": "wheat",
      "y": "cream_cheese",
      "value": 4
    },
    {
      "x": "wheat",
      "y": "yeast",
      "value": 0
    },
    {
      "x": "wheat",
      "y": "rosemary",
      "value": 0
    },
    {
      "x": "wheat",
      "y": "egg",
      "value": 0
    },
    {
      "x": "wheat",
      "y": "milk",
      "value": 0
    },
    {
      "x": "cream_cheese",
      "y": "wheat",
      "value": 4
    },
    {
      "x": "cream_cheese",
      "y": "cream_cheese",
      "value": 0
    },
    {
      "x": "cream_cheese",
      "y": "yeast",
      "value": 0
    },
    {
      "x": "cream_cheese",
      "y": "rosemary",
      "value": 6
    },
    {
      "x": "cream_cheese",
      "y": "egg",
      "value": 27
    },
    {
      "x": "cream_cheese",
      "y": "milk",
      "value": 67
    },
    {
      "x": "yeast",
      "y": "wheat",
      "value": 0
    },
    {
      "x": "yeast",
      "y": "cream_cheese",
      "value": 0
    },
    {
      "x": "yeast",
      "y": "yeast",
      "value": 0
    },
    {
      "x": "yeast",
      "y": "rosemary",
      "value": 0
    },
    {
      "x": "yeast",
      "y": "egg",
      "value": 0
    },
    {
      "x": "yeast",
      "y": "milk",
      "value": 1
    },
    {
      "x": "rosemary",
      "y": "wheat",
      "value": 0
    },
    {
      "x": "rosemary",
      "y": "cream_cheese",
      "value": 6
    },
    {
      "x": "rosemary",
      "y": "yeast",
      "value": 0
    },
    {
      "x": "rosemary",
      "y": "rosemary",
      "value": 0
    },
    {
      "x": "rosemary",
      "y": "egg",
      "value": 2
    },
    {
      "x": "rosemary",
      "y": "milk",
      "value": 3
    },
    {
      "x": "egg",
      "y": "wheat",
      "value": 0
    },
    {
      "x": "egg",
      "y": "cream_cheese",
      "value": 27
    },
    {
      "x": "egg",
      "y": "yeast",
      "value": 0
    },
    {
      "x": "egg",
      "y": "rosemary",
      "value": 2
    },
    {
      "x": "egg",
      "y": "egg",
      "value": 0
    },
    {
      "x": "egg",
      "y": "milk",
      "value": 32
    },
    {
      "x": "milk",
      "y": "wheat",
      "value": 0
    },
    {
      "x": "milk",
      "y": "cream_cheese",
      "value": 67
    },
    {
      "x": "milk",
      "y": "yeast",
      "value": 1
    },
    {
      "x": "milk",
      "y": "rosemary",
      "value": 3
    },
    {
      "x": "milk",
      "y": "egg",
      "value": 32
    },
    {
      "x": "milk",
      "y": "milk",
      "value": 0
    }
  ],
  "contributions": [
    {
      "ingredient": "cream_cheese",
      "mean": 20.8
    },
    {
      "ingredient": "milk",
      "mean": 20.6
    },
    {
      "ingredient": "egg",
      "mean": 12.2
    },
    {
      "ingredient": "rosemary",
      "mean": 2.2
    },
    {
      "ingredient": "wheat",
      "mean": 0.8
    },
    {
      "ingredient": "yeast",
      "mean": 0.2
    }
  ]
}