{
  "id": 44262,
  "cuisine": "NorthAmerican",
  "ingredients": [
    "vinegar",
    "wheat",
    "vegetable_oil",
    "cabbage",
    "black_pepper",
    "chicken"
  ],
  "score_avg": 3.1333333333333333,
  "pair_coverage": 0.5333333333333333,
  "heatmap": [
    {
      "x": "vinegar",
      "y": "vinegar",
      "value": 0
    },
    {
      "x": "vinegar",
      "y": "wheat",
      "value": 0
    },
    {
      "x": "vinegar",
      "y": "vegetable_oil",
      "value": 0
    },
    {
      "x": "vinegar",
      "y": "cabbage",
      "value": 7
    },
    {
      "x": "vinegar",
      "y": "black_pepper",
      "value": 1
    },
    {
      "x": "vinegar",
      "y": "chicken",
      "value": 14
    },
    {
      "x": "wheat",
      "y": "vinegar",
      "value": 0
    },
    {
      "x": "wheat",
      "y": "wheat",
      "value": 0
    },
    {
      "x": "wheat",
      "y": "vegetable_oil",
      "value": 0
    },
    {
      "x": "wheat",
      "y": "cabbage",
      "value": 1
    },
    {
      "x": "wheat",
      "y": "black_pepper",
      "value": 0
    },
    {
      "x": "wheat",
      "y": "chicken",
      "value": 4
    },
    {
      "x": "vegetable_oil",
      "y": "vinegar",
      "value": 0
    },
    {
      "x": "vegetable_oil",
      "y": "wheat",
      "value": 0
    },
    {
      "x": "vegetable_oil",
      "y": "vegetable_oil",
      "value": 0
    },
    {
      "x": "vegetable_oil",
      "y": "cabbage",
      "value": 0
    },
    {
      "x": "vegetable_oil",
      "y": "black_pepper",
      "value": 0
    },
    {
      "x": "vegetable_oil",
      "y": "chicken",
      "value": 1
    },
    {
      "x": "cabbage",
      "y": "vinegar",
      "value": 7
    },
    {
      "x": "cabbage",
      "y": "wheat",
      "value": 1
    },
    {
      "x": "cabbage",
      "y": "vegetable_oil",
      "value": 0
    },
    {
      "x": "cabbage",
      "y": "cabbage",
      "value": 0
    },
    {
      "x": "cabbage",
      "y": "black_pepper",
      "value": 0
    },
    {
      "x": "cabbage",
      "y": "chicken",
      "value": 16
    },
    {
      "x": "black_pepper",
      "y": "vinegar",
      "value": 1
    },
    {
      "x": "black_pepper",
      "y": "wheat",
      "value": 0
    },
    {
      "x": "black_pepper",
      "y": "vegetable_oil",
      "value": 0
    },
    {
      "x": "black_pepper",
      "y": "cabbage",
      "value": 0
    },
    {
      "x": "black_pepper",
      "y": "black_pepper",
      "value": 0
    },
    {
      "x": "black_pepper",
      "y": "chicken",
      "value": 3
    },
    {
      "x": "chicken",
      "y": "vinegar",
      "value": 14
    },
    {
      "x": "chicken",
      "y": "wheat",
      "value": 4
    },
    {
      "x": "chicken",
      "y": "vegetable_oil",
      "value": 1
    },
    {
      "x": "chicken",
      "y": "cabbage",
      "value": 16
    },
    {
      "x": "chicken",
      "y": "black_pepper",
      "value": 3
    },
    {
      "x": "chicken",
      "y": "chicken",
      "value": 0
    }
  ],
  "contributions": [
    {
      "ingredient": "chicken",
      "mean": 7.6
    },
    {
      "ingredient": "cabbage",
      "mean": 4.8
    },
    {
      "ingredient": "vinegar",
      "mean": 4.4
    },
    {
      "ingredient": "wheat",
      "mean": 1.0
    },
    {
      "ingredient": "black_pepper",
      "mean": 0.8
    },
    {
      "ingredient": "vegetable_oil",
      "mean": 0.2
    }
  ]
}