{
  "id": 29921,
  "cuisine": "NorthAmerican",
  "ingredients": [
    "cane_molasses",
    "apple",
    "cream_cheese",
    "vanilla",
    "egg",
    "milk",
    "bread"
  ],
  "score_avg": 22.904761904761905,
  "pair_coverage": 0.7619047619047619,
  "heatmap": [
    {
      "x": "cane_molasses",
      "y": "cane_molasses",
      "value": 0
    },
    {
      "x": "cane_molasses",
      "y": "apple",
      "value": 0
    },
    {
      "x": "cane_molasses",
      "y": "cream_cheese",
      "value": 0
    },
    {
      "x": "cane_molasses",
      "y": "vanilla",
      "value": 0
    },
    {
      "x": "cane_molasses",
      "y": "egg",
      "value": 1
    },
    {
      "x": "cane_molasses",
      "y": "milk",
      "value": 0
    },
    {
      "x": "cane_molasses",
      "y": "bread",
      "value": 0
    },
    {
      "x": "apple",
      "y": "cane_molasses",
      "value": 0
    },
    {
      "x": "apple",
      "y": "apple",
      "value": 0
    },
    {
      "x": "apple",
      "y": "cream_cheese",
      "value": 73
    },
    {
      "x": "apple",
      "y": "vanilla",
      "value": 33
    },
    {
      "x": "apple",
      "y": "egg",
      "value": 15
    },
    {
      "x": "apple",
      "y": "milk",
      "value": 53
    },
    {
      "x": "apple",
      "y": "bread",
      "value": 30
    },
    {
      "x": "cream_cheese",
      "y": "cane_molasses",
      "value": 0
    },
    {
      "x": "cream_cheese",
      "y": "apple",
      "value": 73
    },
    {
      "x": "cream_cheese",
      "y": "cream_cheese",
      "value": 0
    },
    {
      "x": "cream_cheese",
      "y": "vanilla",
      "value": 27
    },
    {
      "x": "cream_cheese",
      "y": "egg",
      "value": 27
    },
    {
      "x": "cream_cheese",
      "y": "milk",
      "value": 67
    },
    {
      "x": "cream_cheese",
      "y": "bread",
      "value": 39
    },
    {
      "x": "vanilla",
      "y": "cane_molasses",
      "value": 0
    },
    {
      "x": "vanilla",
      "y": "apple",
      "value": 33
    },
    {
      "x": "vanilla",
      "y": "cream_cheese",
      "value": 27
    },
    {
      "x": "vanilla",
      "y": "vanilla",
      "value": 0
    },
    {
      "x": "vanilla",
      "y": "egg",
      "value": 8
    },
    {
      "x": "vanilla",
      "y": "milk",
      "value": 23
    },
    {
      "x": "vanilla",
      "y": "bread",
      "value": 10
    },
    {
      "x": "egg",
      "y": "cane_molasses",
      "value": 1
    },
    {
      "x": "egg",
      "y": "apple",
      "value": 15
    },
    {
      "x": "egg",
      "y": "cream_cheese",
      "value": 27
    },
    {
      "x": "egg",
      "y": "vanilla",
      "value": 8
    },
    {
      "x": "egg",
      "y": "egg",
      "value": 0
    },
    {
      "x": "egg",
      "y": "milk",
      "value": 32
    },
    {
      "x": "egg",
      "y": "bread",
      "value": 15
    },
    {
      "x": "milk",
      "y": "cane_molasses",
      "value": 0
    },
    {
      "x": "milk",
      "y": "apple",
      "value": 53
    },
    {
      "x": "milk",
      "y": "cream_cheese",
      "value": 67
    },
    {
      "x": "milk",
      "y": "vanilla",
      "value": 23
    },
    {
      "x": "milk",
      "y": "egg",
      "value": 32
    },
    {
      "x": "milk",
      "y": "milk",
      "value": 0
    },
    {
      "x": "milk",
      "y": "bread",
      "value": 28
    },
    {
      "x": "bread",
      "y": "cane_molasses",
      "value": 0
    },
    {
      "x": "bread",
      "y": "apple",
      "value": 30
    },
    {
      "x": "bread",
      "y": "cream_cheese",
      "value": 39
    },
    {
      "x": "bread",
      "y": "vanilla",
      "value": 10
    },
    {
      "x": "bread",
      "y": "egg",
      "value": 15
    },
    {
      "x": "bread",
      "y": "milk",
      "value": 28
    },
    {
      "x": "bread",
      "y": "bread",
      "value": 0
    }
  ],
  "contributions": [
    {
      "ingredient": "cream_cheese",
      "mean": 38.833333333333336
    },
    {
      "ingredient": "apple",
      "mean": 34.0
    },
    {
      "ingredient": "milk",
      "mean": 33.833333333333336
    },
    {
      "ingredient": "bread",
      "mean": 20.333333333333332
    },
    {
      "ingredient": "vanilla",
      "mean": 16.833333333333332
    },
    {
      "ingredient": "egg",
      "mean": 16.333333333333332
    },
    {
      "ingredient": "cane_molasses",
      "mean": 0.16666666666666666
    }
  ]
}